Workbook
Name IQ_CH: 110000
Name IQ_CQ: 5000
Name IQ_CY: 10000
Name IQ_DAILY: 500000
Name IQ_FH: 100000
Name IQ_FQ: 500
Name IQ_FY: 1000
Name IQ_LTM: 2000
Name IQ_MONTH: 15000
Name IQ_NTM: 6000
Name IQ_WEEK: 50000
Name IQ_YTD: 3000

Sheet Prepared By
A1: CRIZAC LIMITED
A3: Discounted Cash Flow Valuation Model
A5: Prepared By CA Padarabind Pradhan, Research Analyst.
A8: Professional valuation workbook with live formulas, source references, and editable assumptions.
A10: Valuation Date | B10: Equity Value | C10: Value / Share | D10: WACC | E10: Terminal Growth | F10: Projection Period
A11: =Inputs!B6 -> 46207 | B11: =Conclusion!E12 -> 2599.0029 | C11: =Conclusion!E14 -> 148.46016 | D11: =Inputs!B14 -> 0.1626 | E11: =Inputs!B13 -> 0.04 | F11: =Inputs!B12&" Years" -> 7 Years
A14: Model Notes
A15: Purpose: Equity research DCF valuation model for Crizac Limited.
A16: Forecast horizon: 7 years with Gordon Growth terminal value.
A17: Editable assumptions: Inputs tab, highlighted in yellow with blue font.
A18: Source base: Existing Crizac financial workbook, DRHP, Q4 FY2026 results and investor presentation.
A19: Model status: Checks tab should read OK before use.
A22: Color Legend
A23: Input | B23: Editable assumption | C23: Formula | D23: Calculated value | E23: Internal Link | F23: Workbook reference
A25: For research and educational use. Refresh market assumptions before investment use.

Sheet Inputs
A1: Crizac Limited - DCF Valuation Model
A2: Blue/yellow cells are editable inputs. Figures in INR crore unless stated otherwise.
C3: Reason
A4: Company Name | B4: Crizac Limited | C4: Company identifier used across valuation outputs.
A5: Draft/Final | B5: Draft | C5: Draft status indicates assumptions remain editable pending final review.
A6: Valuation Date | B6: 46207 | C6: Valuation date drives discounting and market reference timing.
A7: Next FY end date | B7: 46477 | C7: Defines the first projection fiscal year end for the DCF horizon.
A8: Previous FY end date | B8: 46112 | C8: Anchors historical financials and opening balance sheet inputs.
A9: Currency and Units | B9: Figures in INR Crore | C9: Keeps all model outputs in a consistent reporting unit.
A10: Tax Rate | B10: 0.2517 | C10: Effective tax rate used for FCFF taxes and the WACC tax shield.
A11: Valuation For | B11: Business Valuation | C11: Model prepared on a business valuation basis.
A12: Projection Period (Years) | B12: 7 | C12: Seven-year explicit forecast balances visibility with terminal normalization.
A13: Terminal Period Growth Rate | B13: 0.04 | C13: Terminal growth set below WACC and aligned with mature nominal growth.
A14: WACC | B14: =WACC!C23 -> 0.1626 | C14: Linked to the WACC build-up on the WACC sheet.
A15: Months till NFY | B15: 12 | C15: Assumes a full next fiscal year for discounting from the valuation date.
A17: Cost of Capital Components
A18: Component | B18: Value | C18: Reason
A19: Risk-free rate | B19: 0.068 | C19: Based on prevailing India 10Y government yield as the INR sovereign base rate.
A20: Equity Risk Premium | B20: 0.0746 | C20: Reflects a long-term Indian equity market risk premium assumption. | D20: https://economictimes.indiatimes.com/markets/stocks/news/aswath-damodaran-flags-rise-in-global-risk-premiums-after-u-s-treasury-downgrade/articleshow/123045721.cms
A21: Relevered Beta | B21: 1 | C21: Uses a neutral sector beta pending a refined pure-play peer set.
A22: Company Specific Premium | B22: 0.02 | C22: Adds company-specific execution, concentration and regulatory risk overlay.
A23: Pre-tax Cost of Debt | B23: 0.08 | C23: Reflects estimated marginal borrowing cost for a low-debt business.
A24: Target Debt Weight | B24: 0 | C24: Set to nil because borrowings are immaterial in the current capital structure.
A25: Tax Shield Rate | B25: =B10 -> 0.2517 | C25: Linked to the effective tax rate assumption.
A26: Cost of Equity | B26: =B19+B21*B20+B22 -> 0.1626 | C26: Computed from risk-free rate, beta, ERP and company-specific premium.
A27: After-tax Cost of Debt | B27: =B23*(1-B25) -> 0.059864 | C27: Applies the tax shield to pre-tax debt cost.
A28: WACC | B28: =(1-B24)*B26+B24*B27 -> 0.1626 | C28: Blends equity and debt costs using the target capital structure.
A30: Forecast Operating Assumptions
A31: Particulars | B31: FY2027E | C31: FY2028E | D31: FY2029E | E31: FY2030E | F31: FY2031E | G31: FY2032E | H31: FY2033E | I31: Reason
A32: Revenue Growth | B32: 0.18 | C32: 0.16 | D32: 0.14 | E32: 0.12 | F32: 0.1 | G32: 0.08 | H32: 0.06 | I32: Growth tapers from near-term momentum to a mature terminal profile.
A33: Gross Profit Margin | B33: 0.3 | C33: =B33 -> 0.3 | D33: =C33 -> 0.3 | E33: =D33 -> 0.3 | F33: =E33 -> 0.3 | G33: =F33 -> 0.3 | H33: =G33 -> 0.3 | I33: Margin held steady pending evidence of structural mix or pricing change.
A34: Employee Benefit Expenses % Revenue | B34: 0.03 | C34: 0.03 | D34: 0.03 | E34: 0.03 | F34: 0.03 | G34: 0.03 | H34: 0.03 | I34: Employee cost ratio held stable as scale benefits offset hiring needs.
A35: Advertisement & Marketing Expenses % Revenue | B35: 0.01 | C35: 0.01 | D35: 0.01 | E35: 0.01 | F35: 0.01 | G35: 0.01 | H35: 0.01 | I35: Advertising and marketing ratio kept separate from residual other expenses.
A36: Research & Development Expenses % Revenue | B36: 0 | C36: 0 | D36: 0 | E36: 0 | F36: 0 | G36: 0 | H36: 0 | I36: No separate R&D expense disclosure identified; set to nil until reported or budgeted.
A37: Other Expenses % Revenue | B37: 0.02 | C37: =B37 -> 0.02 | D37: =C37 -> 0.02 | E37: =D37 -> 0.02 | F37: =E37 -> 0.02 | G37: =F37 -> 0.02 | H37: =G37 -> 0.02 | I37: Other operating cost ratio held stable to maintain normalized EBITDA profile.
A38: EBITDA Margin (derived) | B38: =B33-B34-B35-B36-B37 -> 0.24 | C38: =C33-C34-C35-C36-C37 -> 0.24 | D38: =D33-D34-D35-D36-D37 -> 0.24 | E38: =E33-E34-E35-E36-E37 -> 0.24 | F38: =F33-F34-F35-F36-F37 -> 0.24 | G38: =G33-G34-G35-G36-G37 -> 0.24 | H38: =H33-H34-H35-H36-H37 -> 0.24 | I38: Derived from gross margin less employee, marketing and other expense ratios.
A39: D&A % of Revenue | B39: 0.025 | C39: 0.025 | D39: 0.025 | E39: 0.025 | F39: 0.025 | G39: 0.025 | H39: 0.025 | I39: D&A ratio held stable, consistent with an asset-light reinvestment profile.
A40: Capex % of Revenue | B40: 0.02 | C40: =B40 -> 0.02 | D40: =C40 -> 0.02 | E40: =D40 -> 0.02 | F40: =E40 -> 0.02 | G40: =F40 -> 0.02 | H40: =G40 -> 0.02 | I40: Capex ratio assumes maintenance and technology reinvestment needs.
A41: Target NWC % of Revenue | B41: 0.01 | C41: 0.01 | D41: 0.01 | E41: 0.01 | F41: 0.01 | G41: 0.01 | H41: 0.01 | I41: NWC set at 1.0% of revenue, reflecting light working-capital intensity.
A43: Equity Bridge Inputs
A44: Particulars | B44: Value | C44: Reason
A45: Cash and cash equivalents | B45: 135.5434 | C45: Added to enterprise value as non-operating cash available to equity holders.
A46: Other bank balances / surplus cash | B46: 29.4936 | C46: Added as surplus liquidity outside operating cash needs.
A47: Investments | B47: 30.996 | C47: Added as non-core financial assets.
A48: Gross debt | B48: 1.7549 | C48: Deducted from enterprise value to arrive at equity value.
A49: Shares outstanding (crore) | B49: 17.5064 | C49: Used to convert total equity value into value per share.

Sheet TOC
A1: Crizac Limited - DCF Model Table of Contents
A3: Tab | B3: Purpose | C3: Status
A4: Prepared By | B4: Cover, authorship and model summary | C4: Cover
A5: Inputs | B5: Editable model assumptions, terminal growth and WACC components | C5: Editable
A6: Conclusion | B6: Valuation summary and value per share | C6: Output
A7: DCF | B7: 7-year discounted cash flow valuation | C7: Output
A8: WACC | B8: Cost of equity, debt and WACC build-up | C8: Calculation
A9: PL&BS | B9: P&L bridge, broad balance sheet line items and forecast driver schedule | C9: Calculation
A10: WC Movement | B10: Working capital bridge | C10: Support
A11: Sources | B11: Source files and assumption references | C11: Audit
A12: Checks | B12: Model integrity checks | C12: Audit

Sheet Conclusion
B2: =Inputs!B4 -> Crizac Limited
B3: =Inputs!B6 -> 46207
B4: Valuation Conclusion
B5: =Inputs!B9 -> Figures in INR Crore
B7: Particulars | C7: Value | D7: Weight | E7: Weighted Value | G7: Key Assumptions
B8: Discounted Cash Flow Method | C8: =DCF!E37 -> 2599.0029 | D8: 1 | E8: =C8*D8 -> 2599.0029 | G8: Terminal Growth | H8: =Inputs!B13 -> 0.04
B9: Comparable Companies Multiple Method | D9: 0 | E9: =C9*D9 -> 0 | G9: WACC | H9: =WACC!C23 -> 0.1626
B10: Comparable Transaction Method | D10: 0 | E10: =C10*D10 -> 0 | G10: Projection Period | H10: =Inputs!B12&" Years" -> 7 Years
B11: Price of Recent Investment Method | D11: 0 | E11: =C11*D11 -> 0
B12: Concluded Equity Value | E12: =SUM(E8:E11) -> 2599.0029
B13: Outstanding Shares (crore) | E13: =DCF!E38 -> 17.5064
B14: Value per Share | E14: =IFERROR(E12/E13,0) -> 148.46016

Sheet DCF
C2: =Inputs!B4 -> Crizac Limited
C3: =Inputs!B6 -> 46207
C4: Discounted Cash Flow Analysis
C5: =Inputs!B9 -> Figures in INR Crore
E6: Projection Period
E7: 46477 | F7: 46843 | G7: 47208 | H7: 47573 | I7: 47938 | J7: 48304 | K7: 48669 | L7: Terminal Year
E8: 12 | F8: 12 | G8: 12 | H8: 12 | I8: 12 | J8: 12 | K8: 12 | L8: =K7 -> 48669
C10: Revenue | E10: ='PL&BS'!H6 -> 1229.7454 | F10: ='PL&BS'!I6 -> 1426.5046 | G10: ='PL&BS'!J6 -> 1626.2153 | H10: ='PL&BS'!K6 -> 1821.3611 | I10: ='PL&BS'!L6 -> 2003.4972 | J10: ='PL&BS'!M6 -> 2163.777 | K10: ='PL&BS'!N6 -> 2293.6036
C11: % growth | E11: ='PL&BS'!H7 -> 0.18 | F11: ='PL&BS'!I7 -> 0.16 | G11: ='PL&BS'!J7 -> 0.14 | H11: ='PL&BS'!K7 -> 0.12 | I11: ='PL&BS'!L7 -> 0.1 | J11: ='PL&BS'!M7 -> 0.08 | K11: ='PL&BS'!N7 -> 0.06
C12: EBITDA | E12: ='PL&BS'!H20 -> 295.13889 | F12: ='PL&BS'!I20 -> 342.36111 | G12: ='PL&BS'!J20 -> 390.29167 | H12: ='PL&BS'!K20 -> 437.12667 | I12: ='PL&BS'!L20 -> 480.83934 | J12: ='PL&BS'!M20 -> 519.30648 | K12: ='PL&BS'!N20 -> 550.46487
C13: EBITDA margin | E13: ='PL&BS'!H21 -> 0.24 | F13: ='PL&BS'!I21 -> 0.24 | G13: ='PL&BS'!J21 -> 0.24 | H13: ='PL&BS'!K21 -> 0.24 | I13: ='PL&BS'!L21 -> 0.24 | J13: ='PL&BS'!M21 -> 0.24 | K13: ='PL&BS'!N21 -> 0.24
C14: Depreciation & amortisation | E14: ='PL&BS'!H22 -> 30.743634 | F14: ='PL&BS'!I22 -> 35.662616 | G14: ='PL&BS'!J22 -> 40.655382 | H14: ='PL&BS'!K22 -> 45.534028 | I14: ='PL&BS'!L22 -> 50.087431 | J14: ='PL&BS'!M22 -> 54.094425 | K14: ='PL&BS'!N22 -> 57.340091
C15: EBIT | E15: =E12-E14 -> 264.39526 | F15: =F12-F14 -> 306.6985 | G15: =G12-G14 -> 349.63629 | H15: =H12-H14 -> 391.59264 | I15: =I12-I14 -> 430.75191 | J15: =J12-J14 -> 465.21206 | K15: =K12-K14 -> 493.12478
C16: Taxes on EBIT | E16: ='PL&BS'!H25 -> 66.548286 | F16: ='PL&BS'!I25 -> 77.196012 | G16: ='PL&BS'!J25 -> 88.003453 | H16: ='PL&BS'!K25 -> 98.563868 | I16: ='PL&BS'!L25 -> 108.42025 | J16: ='PL&BS'!M25 -> 117.09387 | K16: ='PL&BS'!N25 -> 124.11951
C17: NOPAT | E17: =E15-E16 -> 197.84697 | F17: =F15-F16 -> 229.50249 | G17: =G15-G16 -> 261.63283 | H17: =H15-H16 -> 293.02877 | I17: =I15-I16 -> 322.33165 | J17: =J15-J16 -> 348.11818 | K17: =K15-K16 -> 369.00527
C19: Plus: D&A | E19: =E14 -> 30.743634 | F19: =F14 -> 35.662616 | G19: =G14 -> 40.655382 | H19: =H14 -> 45.534028 | I19: =I14 -> 50.087431 | J19: =J14 -> 54.094425 | K19: =K14 -> 57.340091
C20: Less: Capital Expenditure | E20: =-'PL&BS'!H28 -> -24.594908 | F20: =-'PL&BS'!I28 -> -28.530093 | G20: =-'PL&BS'!J28 -> -32.524306 | H20: =-'PL&BS'!K28 -> -36.427222 | I20: =-'PL&BS'!L28 -> -40.069945 | J20: =-'PL&BS'!M28 -> -43.27554 | K20: =-'PL&BS'!N28 -> -45.872073
C21: Less: Increase/(Decrease) in WC | E21: =-'PL&BS'!H32 -> -7.3864669 | F21: =-'PL&BS'!I32 -> -1.9675926 | G21: =-'PL&BS'!J32 -> -1.9971065 | H21: =-'PL&BS'!K32 -> -1.9514583 | I21: =-'PL&BS'!L32 -> -1.8213611 | J21: =-'PL&BS'!M32 -> -1.6027978 | K21: =-'PL&BS'!N32 -> -1.2982662
C23: Free Cash Flows | E23: =SUM(E17,E19:E21) -> 196.60923 | F23: =SUM(F17,F19:F21) -> 234.66742 | G23: =SUM(G17,G19:G21) -> 267.7668 | H23: =SUM(H17,H19:H21) -> 300.18412 | I23: =SUM(I17,I19:I21) -> 330.52778 | J23: =SUM(J17,J19:J21) -> 357.33427 | K23: =SUM(K17,K19:K21) -> 379.17503
C25: Discount Period | E25: =E8/24 -> 0.5 | F25: =E25+1 -> 1.5 | G25: =F25+1 -> 2.5 | H25: =G25+1 -> 3.5 | I25: =H25+1 -> 4.5 | J25: =I25+1 -> 5.5 | K25: =J25+1 -> 6.5
C26: Discount Factor | D26: =WACC!C23 -> 0.1626 | E26: =1/((1+$D$26)^E25) -> 0.9274379 | F26: =1/((1+$D$26)^F25) -> 0.79772742 | G26: =1/((1+$D$26)^G25) -> 0.68615811 | H26: =1/((1+$D$26)^H25) -> 0.59019277 | I26: =1/((1+$D$26)^I25) -> 0.50764904 | J26: =1/((1+$D$26)^J25) -> 0.43664978 | K26: =1/((1+$D$26)^K25) -> 0.37558041
C27: Present Value of Free Cash Flows | E27: =E23*E26 -> 182.34285 | F27: =F23*F26 -> 187.20063 | G27: =G23*G26 -> 183.73036 | H27: =H23*H26 -> 177.1665 | I27: =I23*I26 -> 167.79211 | J27: =J23*J26 -> 156.02993 | K27: =K23*K26 -> 142.41071
C30: Implied Equity Value | H30: Terminal Value Assumptions
C31: Cumulative Present value of free cash flows | E31: =SUM(E27:K27) -> 1196.6731 | H31: Terminal Model | L31: Gordon Growth
C32: Present Value of Terminal Value | E32: =L36 -> 1208.0517 | H32: Terminal FCF | L32: =K23*(1+Inputs!B13) -> 394.34203
C33: Implied Enterprise Value | E33: =SUM(E31:E32) -> 2404.7248 | H33: Terminal Growth Rate | L33: =Inputs!B13 -> 0.04
C34: Add: Cash and cash equivalents | E34: =Inputs!B45 -> 135.5434 | H34: WACC | L34: =WACC!C23 -> 0.1626
C35: Add: Other bank balances and investments | E35: =Inputs!B46+Inputs!B47 -> 60.4896 | H35: Terminal Value | L35: =L32/(L34-L33) -> 3216.4929
C36: Less: Gross debt | E36: =-Inputs!B48 -> -1.7549 | H36: PV of Terminal Value | L36: =L35*K26 -> 1208.0517
C37: Implied Equity Value | E37: =SUM(E33:E36) -> 2599.0029 | H37: Terminal Value as % of EV | L37: =IFERROR(L36/E33,0) -> 0.50236589
C38: Outstanding Shares (crore) | E38: =Inputs!B49 -> 17.5064
C39: Implied Value per Share | E39: =IFERROR(E37/E38,0) -> 148.46016
C41: Trailing Multiple | D41: FY24 | E41: FY25 | F41: FY26
C42: EV/EBITDA | D42: =$E$33/'PL&BS'!E20 -> 33.102869 | E42: =$E$33/'PL&BS'!F20 -> 11.29923 | F42: =$E$33/'PL&BS'!G20 -> 8.5146542
C43: EV/Revenue | D43: =$E$33/'PL&BS'!E6 -> 3.7877675 | E43: =$E$33/'PL&BS'!F6 -> 2.8307831 | F43: =$E$33/'PL&BS'!G6 -> 2.3074494
C46: Sensitivity: Value per Share
D47: =WACC!C23-1% -> 0.1526 | E47: =WACC!C23-0.5% -> 0.1576 | F47: =WACC!C23 -> 0.1626 | G47: =WACC!C23+0.5% -> 0.1676 | H47: =WACC!C23+1% -> 0.1726
C48: =Inputs!B13-1% -> 0.03 | D48: =IFERROR((E31+L32/(D$47-$C48)*K26+Inputs!B41+Inputs!B42+Inputs!B43-Inputs!B44)/Inputs!B45,0) -> 0 | E48: =IFERROR(($E$31+$L$32/(E$47-$C48)*$K$26+Inputs!$B$45+Inputs!$B$46+Inputs!$B$47-Inputs!$B$48)/Inputs!$B$49,0) -> 145.75615 | F48: =IFERROR(($E$31+$L$32/(F$47-$C48)*$K$26+Inputs!$B$45+Inputs!$B$46+Inputs!$B$47-Inputs!$B$48)/Inputs!$B$49,0) -> 143.25606 | G48: =IFERROR(($E$31+$L$32/(G$47-$C48)*$K$26+Inputs!$B$45+Inputs!$B$46+Inputs!$B$47-Inputs!$B$48)/Inputs!$B$49,0) -> 140.93767 | H48: =IFERROR((E31+L32/(H$47-$C48)*K26+Inputs!B41+Inputs!B42+Inputs!B43-Inputs!B44)/Inputs!B45,0) -> 0
C49: =Inputs!B13 -> 0.04 | D49: =IFERROR((E31+L32/(D$47-$C49)*K26+Inputs!B41+Inputs!B42+Inputs!B43-Inputs!B44)/Inputs!B45,0) -> 0 | E49: =IFERROR(($E$31+$L$32/(E$47-$C49)*$K$26+Inputs!$B$45+Inputs!$B$46+Inputs!$B$47-Inputs!$B$48)/Inputs!$B$49,0) -> 151.3941 | F49: =IFERROR(($E$31+$L$32/(F$47-$C49)*$K$26+Inputs!$B$45+Inputs!$B$46+Inputs!$B$47-Inputs!$B$48)/Inputs!$B$49,0) -> 148.46016 | G49: =IFERROR(($E$31+$L$32/(G$47-$C49)*$K$26+Inputs!$B$45+Inputs!$B$46+Inputs!$B$47-Inputs!$B$48)/Inputs!$B$49,0) -> 145.75615 | H49: =IFERROR((E31+L32/(H$47-$C49)*K26+Inputs!B41+Inputs!B42+Inputs!B43-Inputs!B44)/Inputs!B45,0) -> 0
C50: =Inputs!B13+1% -> 0.05 | D50: =IFERROR((E31+L32/(D$47-$C50)*K26+Inputs!B41+Inputs!B42+Inputs!B43-Inputs!B44)/Inputs!B45,0) -> 0 | E50: =IFERROR(($E$31+$L$32/(E$47-$C50)*$K$26+Inputs!$B$45+Inputs!$B$46+Inputs!$B$47-Inputs!$B$48)/Inputs!$B$49,0) -> 158.07999 | F50: =IFERROR(($E$31+$L$32/(F$47-$C50)*$K$26+Inputs!$B$45+Inputs!$B$46+Inputs!$B$47-Inputs!$B$48)/Inputs!$B$49,0) -> 154.5886 | G50: =IFERROR(($E$31+$L$32/(G$47-$C50)*$K$26+Inputs!$B$45+Inputs!$B$46+Inputs!$B$47-Inputs!$B$48)/Inputs!$B$49,0) -> 151.3941 | H50: =IFERROR((E31+L32/(H$47-$C50)*K26+Inputs!B41+Inputs!B42+Inputs!B43-Inputs!B44)/Inputs!B45,0) -> 0

Sheet WACC
B1: =Inputs!B4 -> Crizac Limited
B2: =Inputs!B6 -> 46207
B3: Estimate of Discount Rate
B5: Cost of Equity Assumptions | C5: Value | D5: Source / Notes
B6: Risk-free rate | C6: =Inputs!B19 -> 0.068 | D6: India sovereign curve / CCIL reference | E6: Ok
B7: Equity Risk Premium | C7: =Inputs!B20 -> 0.0746 | D7: Editable market premium
B8: Relevered Beta | C8: =Inputs!B21 -> 1 | D8: Sector beta placeholder
B9: Company Specific Premium | C9: =Inputs!B22 -> 0.02 | D9: The Crizac-specific risks like UK concentration, visa/policy risk, execution risk and regulatory exposure
B10: Cost of Equity | C10: =C6+C8*C7+C9 -> 0.1626 | D10: Rf + Beta x ERP + CSP
B13: WACC Calculation | C13: Value | D13: Formula / Note
B14: Equity Weight | C14: =1-C15 -> 1 | D14: 1 - debt weight
B15: Debt Weight | C15: =Inputs!B24 -> 0 | D15: Target capital structure input
B16: Cost of Equity | C16: =C10 -> 0.1626 | D16: From CAPM build-up
B17: Pre-tax Cost of Debt | C17: =Inputs!B23 -> 0.08 | D17: Editable input
B18: Tax Rate | C18: =Inputs!B10 -> 0.2517 | D18: Input tax rate
B19: After-tax Cost of Debt | C19: =C17*(1-C18) -> 0.059864 | D19: Kd x (1 - tax)
B20: WACC | C20: =C14*C16+C15*C19 -> 0.1626 | D20: Weighted cost of capital
B23: Final WACC Used in DCF | C23: =C20 -> 0.1626

Sheet PL&BS
A1: Crizac Limited - P&L and Broad Balance Sheet Schedule
A2: Historical values sourced from existing Crizac financial workbook; forecast formulas link to the Inputs tab.
A4: Particulars | B4: Unit | C4: FY2022A | D4: FY2023A | E4: FY2024A | F4: FY2025A | G4: FY2026A | H4: FY2027E | I4: FY2028E | J4: FY2029E | K4: FY2030E | L4: FY2031E | M4: FY2032E | N4: FY2033E
A5: Profit & Loss
A6: Revenue from operations | B6: INR Cr | C6: 263.53 | D6: 472.974 | E6: 634.866 | F6: 849.491 | G6: 1042.1571 | H6: =G6*(1+Inputs!B32) -> 1229.7454 | I6: =H6*(1+Inputs!C32) -> 1426.5046 | J6: =I6*(1+Inputs!D32) -> 1626.2153 | K6: =J6*(1+Inputs!E32) -> 1821.3611 | L6: =K6*(1+Inputs!F32) -> 2003.4972 | M6: =L6*(1+Inputs!G32) -> 2163.777 | N6: =M6*(1+Inputs!H32) -> 2293.6036
A7: YoY revenue growth | B7: % | D7: =D6/C6-1 -> 0.7947634 | E7: =E6/D6-1 -> 0.3422852 | F7: =F6/E6-1 -> 0.33806347 | G7: =G6/F6-1 -> 0.22680181 | H7: =H6/G6-1 -> 0.18 | I7: =I6/H6-1 -> 0.16 | J7: =J6/I6-1 -> 0.14 | K7: =K6/J6-1 -> 0.12 | ... N7: =N6/M6-1 -> 0.06
A8: Cost of services | B8: INR Cr | D8: 307.612 | E8: 444.636 | F8: 599.238 | G8: 703.1954 | H8: =H6*(1-Inputs!B33) -> 860.82176 | I8: =I6*(1-Inputs!C33) -> 998.55325 | J8: =J6*(1-Inputs!D33) -> 1138.3507 | K8: =K6*(1-Inputs!E33) -> 1274.9528 | L8: =L6*(1-Inputs!F33) -> 1402.4481 | M8: =M6*(1-Inputs!G33) -> 1514.6439 | N8: =N6*(1-Inputs!H33) -> 1605.5225
A9: Cost of services / revenue | B9: % | D9: =IFERROR(D8/D6,0) -> 0.65037824 | E9: =IFERROR(E8/E6,0) -> 0.70036197 | F9: =IFERROR(F8/F6,0) -> 0.7054083 | G9: =IFERROR(G8/G6,0) -> 0.6747499 | H9: =IFERROR(H8/H6,0) -> 0.7 | I9: =IFERROR(I8/I6,0) -> 0.7 | J9: =IFERROR(J8/J6,0) -> 0.7 | K9: =IFERROR(K8/K6,0) -> 0.7 | ... N9: =IFERROR(N8/N6,0) -> 0.7
A10: Gross Profit | B10: INR Cr | D10: =D6-D8 -> 165.362 | E10: =E6-E8 -> 190.23 | F10: =F6-F8 -> 250.253 | G10: =G6-G8 -> 338.9617 | H10: =H6-H8 -> 368.92361 | I10: =I6-I8 -> 427.95139 | J10: =J6-J8 -> 487.86459 | K10: =K6-K8 -> 546.40834 | ... N10: =N6-N8 -> 688.08109
A11: Gross Profit Margin | B11: % | D11: =IFERROR(D10/D6,0) -> 0.34962176 | E11: =IFERROR(E10/E6,0) -> 0.29963803 | F11: =IFERROR(F10/F6,0) -> 0.2945917 | G11: =IFERROR(G10/G6,0) -> 0.3252501 | H11: =IFERROR(H10/H6,0) -> 0.3 | I11: =IFERROR(I10/I6,0) -> 0.3 | J11: =IFERROR(J10/J6,0) -> 0.3 | K11: =IFERROR(K10/K6,0) -> 0.3 | ... N11: =IFERROR(N10/N6,0) -> 0.3
A12: Employee Benefit Expenses | B12: INR Cr | D12: 4.043 | E12: 6.688 | F12: 19.162 | G12: 30.3451 | H12: =H6*Inputs!B34 -> 36.892361 | I12: =I6*Inputs!C34 -> 42.795139 | J12: =J6*Inputs!D34 -> 48.786459 | K12: =K6*Inputs!E34 -> 54.640834 | L12: =L6*Inputs!F34 -> 60.104917 | M12: =M6*Inputs!G34 -> 64.91331 | N12: =N6*Inputs!H34 -> 68.808109
A13: Employee Benefit % Revenue | B13: % | D13: =IFERROR(D12/D6,0) -> 0.0085480386 | E13: =IFERROR(E12/E6,0) -> 0.010534506 | F13: =IFERROR(F12/F6,0) -> 0.022557037 | G13: =IFERROR(G12/G6,0) -> 0.029117587 | H13: =IFERROR(H12/H6,0) -> 0.03 | I13: =IFERROR(I12/I6,0) -> 0.03 | J13: =IFERROR(J12/J6,0) -> 0.03 | K13: =IFERROR(K12/K6,0) -> 0.03 | ... N13: =IFERROR(N12/N6,0) -> 0.03
A14: Advertisement & Marketing Expenses | B14: INR Cr | D14: 0.027 | E14: 1.339 | F14: 0.262 | G14: 0 | H14: =H6*Inputs!B35 -> 12.297454 | I14: =I6*Inputs!C35 -> 14.265046 | J14: =J6*Inputs!D35 -> 16.262153 | K14: =K6*Inputs!E35 -> 18.213611 | L14: =L6*Inputs!F35 -> 20.034972 | M14: =M6*Inputs!G35 -> 21.63777 | N14: =N6*Inputs!H35 -> 22.936036
A15: Advertisement & Marketing % Revenue | B15: % | D15: =IFERROR(D14/D6,0) -> 5.708559e-05 | E15: =IFERROR(E14/E6,0) -> 0.0021091065 | F15: =IFERROR(F14/F6,0) -> 0.00030841998 | G15: =IFERROR(G14/G6,0) -> 0 | H15: =IFERROR(H14/H6,0) -> 0.01 | I15: =IFERROR(I14/I6,0) -> 0.01 | J15: =IFERROR(J14/J6,0) -> 0.01 | K15: =IFERROR(K14/K6,0) -> 0.01 | ... N15: =IFERROR(N14/N6,0) -> 0.01
A16: Research & Development Expenses | B16: INR Cr | C16: 0 | D16: 0 | E16: 0 | F16: 0 | G16: 0 | H16: =H6*Inputs!B36 -> 0 | I16: =I6*Inputs!C36 -> 0 | J16: =J6*Inputs!D36 -> 0 | K16: =K6*Inputs!E36 -> 0 | L16: =L6*Inputs!F36 -> 0 | M16: =M6*Inputs!G36 -> 0 | N16: =N6*Inputs!H36 -> 0
A17: Research & Development % Revenue | B17: % | D17: =IFERROR(D16/D6,0) -> 0 | E17: =IFERROR(E16/E6,0) -> 0 | F17: =IFERROR(F16/F6,0) -> 0 | G17: =IFERROR(G16/G6,0) -> 0 | H17: =IFERROR(H16/H6,0) -> 0 | I17: =IFERROR(I16/I6,0) -> 0 | J17: =IFERROR(J16/J6,0) -> 0 | K17: =IFERROR(K16/K6,0) -> 0 | ... N17: =IFERROR(N16/N6,0) -> 0
A18: Other Expenses | B18: INR Cr | D18: 54.007 | E18: 109.559 | F18: 18.007 | G18: 26.1947 | H18: =H6*Inputs!B37 -> 24.594908 | I18: =I6*Inputs!C37 -> 28.530093 | J18: =J6*Inputs!D37 -> 32.524306 | K18: =K6*Inputs!E37 -> 36.427222 | L18: =L6*Inputs!F37 -> 40.069945 | M18: =M6*Inputs!G37 -> 43.27554 | N18: =N6*Inputs!H37 -> 45.872073
A19: Other Expenses % Revenue | B19: % | D19: =IFERROR(D18/D6,0) -> 0.11418598 | E19: =IFERROR(E18/E6,0) -> 0.17257027 | F19: =IFERROR(F18/F6,0) -> 0.021197399 | G19: =IFERROR(G18/G6,0) -> 0.025135078 | H19: =IFERROR(H18/H6,0) -> 0.02 | I19: =IFERROR(I18/I6,0) -> 0.02 | J19: =IFERROR(J18/J6,0) -> 0.02 | K19: =IFERROR(K18/K6,0) -> 0.02 | ... N19: =IFERROR(N18/N6,0) -> 0.02
A20: EBITDA | B20: INR Cr | D20: =D10-D12-D14-D16-D18 -> 107.285 | E20: =E10-E12-E14-E16-E18 -> 72.644 | F20: =F10-F12-F14-F16-F18 -> 212.822 | G20: =G10-G12-G14-G16-G18 -> 282.4219 | H20: =H10-H12-H14-H16-H18 -> 295.13889 | I20: =I10-I12-I14-I16-I18 -> 342.36111 | J20: =J10-J12-J14-J16-J18 -> 390.29167 | K20: =K10-K12-K14-K16-K18 -> 437.12667 | ... N20: =N10-N12-N14-N16-N18 -> 550.46487
A21: EBITDA margin | B21: % | D21: =IFERROR(D20/D6,0) -> 0.22683065 | E21: =IFERROR(E20/E6,0) -> 0.11442415 | F21: =IFERROR(F20/F6,0) -> 0.25052885 | G21: =IFERROR(G20/G6,0) -> 0.27099743 | H21: =IFERROR(H20/H6,0) -> 0.24 | I21: =IFERROR(I20/I6,0) -> 0.24 | J21: =IFERROR(J20/J6,0) -> 0.24 | K21: =IFERROR(K20/K6,0) -> 0.24 | ... N21: =IFERROR(N20/N6,0) -> 0.24
A22: Depreciation & amortisation | B22: INR Cr | D22: 2.153 | E22: 13.433 | F22: 45.655 | G22: 27.3628 | H22: =H6*Inputs!B39 -> 30.743634 | I22: =I6*Inputs!C39 -> 35.662616 | J22: =J6*Inputs!D39 -> 40.655382 | K22: =K6*Inputs!E39 -> 45.534028 | L22: =L6*Inputs!F39 -> 50.087431 | M22: =M6*Inputs!G39 -> 54.094425 | N22: =N6*Inputs!H39 -> 57.340091
A23: D&A % of revenue | B23: % | D23: =IFERROR(D22/D6,0) -> 0.0045520473 | E23: =IFERROR(E22/E6,0) -> 0.021158796 | F23: =IFERROR(F22/F6,0) -> 0.053743948 | G23: =IFERROR(G22/G6,0) -> 0.026255926 | H23: =IFERROR(H22/H6,0) -> 0.025 | I23: =IFERROR(I22/I6,0) -> 0.025 | J23: =IFERROR(J22/J6,0) -> 0.025 | K23: =IFERROR(K22/K6,0) -> 0.025 | ... N23: =IFERROR(N22/N6,0) -> 0.025
A24: EBIT | B24: INR Cr | D24: =D20-D22 -> 105.132 | E24: =E20-E22 -> 59.211 | F24: =F20-F22 -> 167.167 | G24: =G20-G22 -> 255.0591 | H24: =H20-H22 -> 264.39526 | I24: =I20-I22 -> 306.6985 | J24: =J20-J22 -> 349.63629 | K24: =K20-K22 -> 391.59264 | ... N24: =N20-N22 -> 493.12478
A25: Tax on EBIT | B25: INR Cr | D25: 26.461724 | E25: 14.903409 | F25: 42.075934 | G25: 64.198375 | H25: =MAX(0,H24*Inputs!$B$10) -> 66.548286 | I25: =MAX(0,I24*Inputs!$B$10) -> 77.196012 | J25: =MAX(0,J24*Inputs!$B$10) -> 88.003453 | K25: =MAX(0,K24*Inputs!$B$10) -> 98.563868 | L25: =MAX(0,L24*Inputs!$B$10) -> 108.42025 | M25: =MAX(0,M24*Inputs!$B$10) -> 117.09387 | N25: =MAX(0,N24*Inputs!$B$10) -> 124.11951
A26: NOPAT | B26: INR Cr | D26: =D24-D25 -> 78.670276 | E26: =E24-E25 -> 44.307591 | F26: =F24-F25 -> 125.09107 | G26: =G24-G25 -> 190.86072 | H26: =H24-H25 -> 197.84697 | I26: =I24-I25 -> 229.50249 | J26: =J24-J25 -> 261.63283 | K26: =K24-K25 -> 293.02877 | ... N26: =N24-N25 -> 369.00527
A27: Cash Flow Support
A28: Capital expenditure | B28: INR Cr | D28: 1.466 | E28: 120.082 | F28: 1.077 | G28: 16.889 | H28: =H6*Inputs!B40 -> 24.594908 | I28: =I6*Inputs!C40 -> 28.530093 | J28: =J6*Inputs!D40 -> 32.524306 | K28: =K6*Inputs!E40 -> 36.427222 | L28: =L6*Inputs!F40 -> 40.069945 | M28: =M6*Inputs!G40 -> 43.27554 | N28: =N6*Inputs!H40 -> 45.872073
A29: Capex % of revenue | B29: % | D29: =IFERROR(D28/D6,0) -> 0.0030995361 | E29: =IFERROR(E28/E6,0) -> 0.18914543 | F29: =IFERROR(F28/F6,0) -> 0.001267818 | G29: =IFERROR(G28/G6,0) -> 0.01620581 | H29: =IFERROR(H28/H6,0) -> 0.02 | I29: =IFERROR(I28/I6,0) -> 0.02 | J29: =IFERROR(J28/J6,0) -> 0.02 | K29: =IFERROR(K28/K6,0) -> 0.02 | ... N29: =IFERROR(N28/N6,0) -> 0.02
A30: Net working capital | B30: INR Cr | D30: -25.864551 | E30: 37.84845 | F30: -4.1892707 | G30: 4.9109869 | H30: =H6*Inputs!B41 -> 12.297454 | I30: =I6*Inputs!C41 -> 14.265046 | J30: =J6*Inputs!D41 -> 16.262153 | K30: =K6*Inputs!E41 -> 18.213611 | L30: =L6*Inputs!F41 -> 20.034972 | M30: =M6*Inputs!G41 -> 21.63777 | N30: =N6*Inputs!H41 -> 22.936036
A31: NWC % of revenue | B31: % | D31: =IFERROR(D30/D6,0) -> -0.054684932 | E31: =IFERROR(E30/E6,0) -> 0.059616438 | F31: =IFERROR(F30/F6,0) -> -0.0049315068 | G31: =IFERROR(G30/G6,0) -> 0.0047123288 | H31: =IFERROR(H30/H6,0) -> 0.01 | I31: =IFERROR(I30/I6,0) -> 0.01 | J31: =IFERROR(J30/J6,0) -> 0.01 | K31: =IFERROR(K30/K6,0) -> 0.01 | ... N31: =IFERROR(N30/N6,0) -> 0.01
A32: Change in NWC | B32: INR Cr | D32: -25.864551 | E32: 63.713001 | F32: -42.03772 | G32: 9.1002576 | H32: =H30-G30 -> 7.3864669 | I32: =I30-H30 -> 1.9675926 | J32: =J30-I30 -> 1.9971065 | K32: =K30-J30 -> 1.9514583 | L32: =L30-K30 -> 1.8213611 | M32: =M30-L30 -> 1.6027978 | N32: =N30-M30 -> 1.2982662
A34: Balance Sheet - Broad Line Items
A35: Total non-current assets | B35: INR Cr | D35: 52.95 | E35: 177.767 | F35: 279.126 | G35: 301.1539 | H35: =G35+H28-H22 -> 295.00517 | I35: =H35+I28-I22 -> 287.87265 | J35: =I35+J28-J22 -> 279.74157 | K35: =J35+K28-K22 -> 270.63477 | L35: =K35+L28-L22 -> 260.61728 | M35: =L35+M28-M22 -> 249.7984 | N35: =M35+N28-N22 -> 238.33038
A36: Total current assets | B36: INR Cr | D36: 179.113 | E36: 413.26 | F36: 598.614 | G36: 574.4241 | H36: =H6*($G36/$G$6) -> 677.82044 | I36: =I6*($G36/$G$6) -> 786.27171 | J36: =J6*($G36/$G$6) -> 896.34975 | K36: =K6*($G36/$G$6) -> 1003.9117 | L36: =L6*($G36/$G$6) -> 1104.3029 | M36: =M6*($G36/$G$6) -> 1192.6471 | N36: =N6*($G36/$G$6) -> 1264.2059
A37: Total assets | B37: INR Cr | D37: 232.063 | E37: 591.027 | F37: 877.74 | G37: 875.578 | H37: =H35+H36 -> 972.82561 | I37: =I35+I36 -> 1074.1444 | J37: =J35+J36 -> 1176.0913 | K37: =K35+K36 -> 1274.5465 | L37: =L35+L36 -> 1364.9202 | M37: =M35+M36 -> 1442.4455 | N37: =N35+N36 -> 1502.5363
A38: Total equity (implied) | B38: INR Cr | D38: 219.97 | E38: 339.144 | F38: 503.366 | G38: 592.4433 | H38: =H37-H41 -> 638.72667 | I38: =I37-I41 -> 686.58958 | J38: =J37-J41 -> 734.27887 | K38: =K37-K41 -> 779.71655 | L38: =L37-L41 -> 820.60724 | M38: =M37-M41 -> 854.58755 | N38: =N37-N41 -> 879.40688
A39: Total non-current liabilities | B39: INR Cr | D39: 10.935 | E39: 28.243 | F39: 6.651 | G39: 9.9632 | H39: =H6*($G39/$G$6) -> 11.756576 | I39: =I6*($G39/$G$6) -> 13.637628 | J39: =J6*($G39/$G$6) -> 15.546896 | K39: =K6*($G39/$G$6) -> 17.412524 | L39: =L6*($G39/$G$6) -> 19.153776 | M39: =M6*($G39/$G$6) -> 20.686078 | N39: =N6*($G39/$G$6) -> 21.927243
A40: Total current liabilities | B40: INR Cr | D40: 1.158 | E40: 223.64 | F40: 367.723 | G40: 273.1715 | H40: =H6*($G40/$G$6) -> 322.34237 | I40: =I6*($G40/$G$6) -> 373.91715 | J40: =J6*($G40/$G$6) -> 426.26555 | K40: =K6*($G40/$G$6) -> 477.41742 | L40: =L6*($G40/$G$6) -> 525.15916 | M40: =M6*($G40/$G$6) -> 567.17189 | N40: =N6*($G40/$G$6) -> 601.2022
A41: Total liabilities | B41: INR Cr | D41: 12.093 | E41: 251.883 | F41: 374.374 | G41: 283.1347 | H41: =H39+H40 -> 334.09895 | I41: =I39+I40 -> 387.55478 | J41: =J39+J40 -> 441.81245 | K41: =K39+K40 -> 494.82994 | L41: =L39+L40 -> 544.31293 | M41: =M39+M40 -> 587.85797 | N41: =N39+N40 -> 623.12945
A42: Total equity and liabilities | B42: INR Cr | D42: 232.063 | E42: 591.027 | F42: 877.74 | G42: 875.578 | H42: =H38+H41 -> 972.82561 | I42: =I38+I41 -> 1074.1444 | J42: =J38+J41 -> 1176.0913 | K42: =K38+K41 -> 1274.5465 | L42: =L38+L41 -> 1364.9202 | M42: =M38+M41 -> 1442.4455 | N42: =N38+N41 -> 1502.5363
A43: Balance sheet check | B43: INR Cr | D43: =D37-D42 -> 0 | E43: =E37-E42 -> 0 | F43: =F37-F42 -> 0 | G43: =G37-G42 -> 0 | H43: =H37-H42 -> 0 | I43: =I37-I42 -> 0 | J43: =J37-J42 -> 0 | K43: =K37-K42 -> 0 | ... N43: =N37-N42 -> 0
A45: Net Debt & Share Count
A46: Cash and cash equivalents | B46: INR Cr | G46: =Inputs!B45 -> 135.5434
A47: Other bank balances / surplus cash | B47: INR Cr | G47: =Inputs!B46 -> 29.4936
A48: Investments | B48: INR Cr | G48: =Inputs!B47 -> 30.996
A49: Gross debt | B49: INR Cr | G49: =Inputs!B48 -> 1.7549
A50: Shares outstanding (crore) | B50: Crore | G50: =Inputs!B49 -> 17.5064
A52: Modeling Notes
A53: Advertisement/marketing and R&D expense note | B53: Note | C53: Historical advertisement and sales promotion costs are shown separately where disclosed in the DRHP expense note; residual operating cost is retained in Other Expenses so EBITDA remains unchanged. No separate R&D expense disclosure was identified, so R&D is shown as nil until reported or budgeted.
A54: Broad balance sheet forecast note | B54: Note | C54: Forecast balance sheet lines are high-level roll-forward / ratio-based estimates and are intended as broad schedule support, not a full integrated three-statement balance sheet.
A56: Balance Sheet Bifurcation - Detailed Line Items
A57: Particulars | B57: Unit | C57: FY2022A | D57: FY2023A | E57: FY2024A | F57: FY2025A | G57: FY2026A | H57: FY2027E | I57: FY2028E | J57: FY2029E | K57: FY2030E | L57: FY2031E | M57: FY2032E | N57: FY2033E | O57: Projection basis
A58: Non-current assets
A59: Property, plant and equipment | B59: INR Cr | D59: 5.94 | E59: 11.63 | F59: 10.903 | G59: 32.2205 | H59: =H$35*($G59/$G$68) -> 31.562647 | I59: =I$35*($G59/$G$68) -> 30.799537 | J59: =J$35*($G59/$G$68) -> 29.929592 | K59: =K$35*($G59/$G$68) -> 28.955254 | L59: =L$35*($G59/$G$68) -> 27.883481 | M59: =M$35*($G59/$G$68) -> 26.725967 | N59: =N$35*($G59/$G$68) -> 25.499002 | O59: Forecast as FY2026 mix of total non-current assets.
A60: Investment property | B60: INR Cr | D60: 2.185 | E60: 9.098 | F60: 8.234 | G60: 7.4509 | H60: =H$35*($G60/$G$68) -> 7.2987733 | I60: =I$35*($G60/$G$68) -> 7.1223063 | J60: =J$35*($G60/$G$68) -> 6.921134 | K60: =K$35*($G60/$G$68) -> 6.6958209 | L60: =L$35*($G60/$G$68) -> 6.4479766 | M60: =M$35*($G60/$G$68) -> 6.1803047 | N60: =N$35*($G60/$G$68) -> 5.8965725 | O60: Forecast as FY2026 mix of total non-current assets.
A61: Goodwill | B61: INR Cr | D61: 0 | E61: 0.827 | F61: 5.925 | G61: 24.3585 | H61: =H$35*($G61/$G$68) -> 23.861167 | I61: =I$35*($G61/$G$68) -> 23.284261 | J61: =J$35*($G61/$G$68) -> 22.626588 | K61: =K$35*($G61/$G$68) -> 21.889994 | L61: =L$35*($G61/$G$68) -> 21.07974 | M61: =M$35*($G61/$G$68) -> 20.204667 | N61: =N$35*($G61/$G$68) -> 19.277089 | O61: Forecast as FY2026 mix of total non-current assets.
A62: Intangible assets | B62: INR Cr | D62: 0 | E62: 93.23 | F62: 55.435 | G62: 45.1234 | H62: =H$35*($G62/$G$68) -> 44.202105 | I62: =I$35*($G62/$G$68) -> 43.133404 | J62: =J$35*($G62/$G$68) -> 41.915084 | K62: =K$35*($G62/$G$68) -> 40.550565 | L62: =L$35*($G62/$G$68) -> 39.049595 | M62: =M$35*($G62/$G$68) -> 37.428547 | N62: =N$35*($G62/$G$68) -> 35.710237 | O62: Forecast as FY2026 mix of total non-current assets.
A63: Right-of-use assets | B63: INR Cr | D63: 13.56 | E63: 13.549 | F63: 12.268 | G63: 11.1089 | H63: =H$35*($G63/$G$68) -> 10.882087 | I63: =I$35*($G63/$G$68) -> 10.618984 | J63: =J$35*($G63/$G$68) -> 10.319047 | K63: =K$35*($G63/$G$68) -> 9.9831168 | L63: =L$35*($G63/$G$68) -> 9.613594 | M63: =M$35*($G63/$G$68) -> 9.2145093 | N63: =N$35*($G63/$G$68) -> 8.7914795 | O63: Forecast as FY2026 mix of total non-current assets.
A64: Non-current investments | B64: INR Cr | D64: 26.083 | E64: 28.113 | F64: 38.357 | G64: 30.996 | H64: =H$35*($G64/$G$68) -> 30.363148 | I64: =I$35*($G64/$G$68) -> 29.629039 | J64: =J$35*($G64/$G$68) -> 28.792155 | K64: =K$35*($G64/$G$68) -> 27.854845 | L64: =L$35*($G64/$G$68) -> 26.823804 | M64: =M$35*($G64/$G$68) -> 25.71028 | N64: =N$35*($G64/$G$68) -> 24.529944 | O64: Forecast as FY2026 mix of total non-current assets.
A65: Other non-current financial assets | B65: INR Cr | D65: 4.526 | E65: 20.056 | F65: 147.864 | G65: 142.2081 | H65: =H$35*($G65/$G$68) -> 139.30461 | I65: =I$35*($G65/$G$68) -> 135.93655 | J65: =J$35*($G65/$G$68) -> 132.09697 | K65: =K$35*($G65/$G$68) -> 127.79664 | L65: =L$35*($G65/$G$68) -> 123.06627 | M65: =M$35*($G65/$G$68) -> 117.95748 | N65: =N$35*($G65/$G$68) -> 112.54216 | O65: Forecast as FY2026 mix of total non-current assets.
A66: Income tax assets, net | B66: INR Cr | D66: 0 | E66: 0 | F66: 0 | G66: 7.5874 | H66: =H$35*($G66/$G$68) -> 7.4324863 | I66: =I$35*($G66/$G$68) -> 7.2527865 | J66: =J$35*($G66/$G$68) -> 7.0479287 | K66: =K$35*($G66/$G$68) -> 6.8184879 | L66: =L$35*($G66/$G$68) -> 6.5661031 | M66: =M$35*($G66/$G$68) -> 6.2935275 | N66: =N$35*($G66/$G$68) -> 6.0045974 | O66: Forecast as FY2026 mix of total non-current assets.
A67: Other non-current assets | B67: INR Cr | D67: 0.656 | E67: 1.264 | F67: 0.14 | G67: 0.1002 | H67: =H$35-SUM(H59:H66) -> 0.098154194 | I67: =I$35-SUM(I59:I66) -> 0.095781059 | J67: =J$35-SUM(J59:J66) -> 0.093075685 | K67: =K$35-SUM(K59:K66) -> 0.090045667 | L67: =L$35-SUM(L59:L66) -> 0.086712646 | M67: =M$35-SUM(M59:M66) -> 0.083112984 | N67: =N$35-SUM(N59:N66) -> 0.079297342 | O67: Residual line to tie projected total non-current assets exactly.
A68: Total non-current assets - bifurcated | B68: INR Cr | D68: =SUM(D59:D67) -> 52.95 | E68: =SUM(E59:E67) -> 177.767 | F68: =SUM(F59:F67) -> 279.126 | G68: =SUM(G59:G67) -> 301.1539 | H68: =SUM(H59:H67) -> 295.00517 | I68: =SUM(I59:I67) -> 287.87265 | J68: =SUM(J59:J67) -> 279.74157 | K68: =SUM(K59:K67) -> 270.63477 | ... N68: =SUM(N59:N67) -> 238.33038 | O68: Sums detailed non-current asset lines and ties to row 35.
A69: Check: NCA bifurcation vs broad total | B69: INR Cr | D69: =D68-D35 -> 0 | E69: =E68-E35 -> 0 | F69: =F68-F35 -> 0 | G69: =G68-G35 -> 0 | H69: =H68-H35 -> 0 | I69: =I68-I35 -> 0 | J69: =J68-J35 -> 0 | K69: =K68-K35 -> 0 | ... N69: =N68-N35 -> 0 | O69: Check against existing broad total row; should be nil.
A71: Current assets
A72: Current investments | B72: INR Cr | D72: 79.995 | E72: 115.095 | F72: 0 | G72: 0 | H72: =H$36*($G72/$G$79) -> 0 | I72: =I$36*($G72/$G$79) -> 0 | J72: =J$36*($G72/$G$79) -> 0 | K72: =K$36*($G72/$G$79) -> 0 | L72: =L$36*($G72/$G$79) -> 0 | M72: =M$36*($G72/$G$79) -> 0 | N72: =N$36*($G72/$G$79) -> 0 | O72: No current investments in FY2026; forecast as FY2026 mix of total current assets.
A73: Trade receivables | B73: INR Cr | D73: 0 | E73: 167.871 | F73: 256.404 | G73: 238.5121 | H73: =H$36*($G73/$G$79) -> 281.44428 | I73: =I$36*($G73/$G$79) -> 326.47536 | J73: =J$36*($G73/$G$79) -> 372.18191 | K73: =K$36*($G73/$G$79) -> 416.84374 | L73: =L$36*($G73/$G$79) -> 458.52812 | M73: =M$36*($G73/$G$79) -> 495.21037 | N73: =N$36*($G73/$G$79) -> 524.92299 | O73: Forecast as FY2026 mix of total current assets.
A74: Cash and cash equivalents | B74: INR Cr | D74: 15.71 | E74: 50.22 | F74: 88.827 | G74: 135.5434 | H74: =H$36*($G74/$G$79) -> 159.94121 | I74: =I$36*($G74/$G$79) -> 185.53181 | J74: =J$36*($G74/$G$79) -> 211.50626 | K74: =K$36*($G74/$G$79) -> 236.88701 | L74: =L$36*($G74/$G$79) -> 260.57571 | M74: =M$36*($G74/$G$79) -> 281.42177 | N74: =N$36*($G74/$G$79) -> 298.30707 | O74: Forecast as FY2026 mix of total current assets for balance-sheet support.
A75: Other bank balances | B75: INR Cr | D75: 51.5 | E75: 72.812 | F75: 221.785 | G75: 29.4936 | H75: =H$36*($G75/$G$79) -> 34.802448 | I75: =I$36*($G75/$G$79) -> 40.37084 | J75: =J$36*($G75/$G$79) -> 46.022757 | K75: =K$36*($G75/$G$79) -> 51.545488 | L75: =L$36*($G75/$G$79) -> 56.700037 | M75: =M$36*($G75/$G$79) -> 61.23604 | N75: =N$36*($G75/$G$79) -> 64.910202 | O75: Forecast as FY2026 mix of total current assets.
A76: Other financial assets | B76: INR Cr | D76: 22.777 | E76: 4.103 | F76: 15.326 | G76: 170.1441 | H76: =H$36*($G76/$G$79) -> 200.77004 | I76: =I$36*($G76/$G$79) -> 232.89324 | J76: =J$36*($G76/$G$79) -> 265.4983 | K76: =K$36*($G76/$G$79) -> 297.35809 | L76: =L$36*($G76/$G$79) -> 327.0939 | M76: =M$36*($G76/$G$79) -> 353.26142 | N76: =N$36*($G76/$G$79) -> 374.4571 | O76: Forecast as FY2026 mix of total current assets.
A77: Current tax assets, net | B77: INR Cr | D77: 3.484 | E77: 0 | F77: 2.479 | G77: 0 | H77: =H$36*($G77/$G$79) -> 0 | I77: =I$36*($G77/$G$79) -> 0 | J77: =J$36*($G77/$G$79) -> 0 | K77: =K$36*($G77/$G$79) -> 0 | L77: =L$36*($G77/$G$79) -> 0 | M77: =M$36*($G77/$G$79) -> 0 | N77: =N$36*($G77/$G$79) -> 0 | O77: FY2026 tax asset shown in non-current assets; forecast as FY2026 mix.
A78: Other current assets | B78: INR Cr | D78: 5.647 | E78: 3.159 | F78: 13.793 | G78: 0.7309 | H78: =H$36-SUM(H72:H77) -> 0.862462 | I78: =I$36-SUM(I72:I77) -> 1.0004559 | J78: =J$36-SUM(J72:J77) -> 1.1405197 | K78: =K$36-SUM(K72:K77) -> 1.2773821 | L78: =L$36-SUM(L72:L77) -> 1.4051203 | M78: =M$36-SUM(M72:M77) -> 1.51753 | N78: =N$36-SUM(N72:N77) -> 1.6085818 | O78: Residual line to tie projected total current assets exactly.
A79: Total current assets - bifurcated | B79: INR Cr | D79: =SUM(D72:D78) -> 179.113 | E79: =SUM(E72:E78) -> 413.26 | F79: =SUM(F72:F78) -> 598.614 | G79: =SUM(G72:G78) -> 574.4241 | H79: =SUM(H72:H78) -> 677.82044 | I79: =SUM(I72:I78) -> 786.27171 | J79: =SUM(J72:J78) -> 896.34975 | K79: =SUM(K72:K78) -> 1003.9117 | ... N79: =SUM(N72:N78) -> 1264.2059 | O79: Sums detailed current asset lines and ties to row 36.
A80: Check: CA bifurcation vs broad total | B80: INR Cr | D80: =D79-D36 -> 0 | E80: =E79-E36 -> 0 | F80: =F79-F36 -> 0 | G80: =G79-G36 -> 0 | H80: =H79-H36 -> 0 | I80: =I79-I36 -> 0 | J80: =J79-J36 -> 0 | K80: =K79-K36 -> 0 | ... N80: =N79-N36 -> 0 | O80: Check against existing broad total row; should be nil.
A82: Non-current liabilities
A83: Borrowings | B83: INR Cr | D83: 0 | E83: 0 | F83: 0 | G83: 0.8755 | H83: =H$39*($G83/$G$88) -> 1.03309 | I83: =I$39*($G83/$G$88) -> 1.1983844 | J83: =J$39*($G83/$G$88) -> 1.3661582 | K83: =K$39*($G83/$G$88) -> 1.5300972 | L83: =L$39*($G83/$G$88) -> 1.6831069 | M83: =M$39*($G83/$G$88) -> 1.8177555 | N83: =N$39*($G83/$G$88) -> 1.9268208 | O83: Forecast as FY2026 mix of total non-current liabilities.
A84: Lease liabilities | B84: INR Cr | D84: 0.083 | E84: 0.083 | F84: 0.083 | G84: 0.0827 | H84: =H$39*($G84/$G$88) -> 0.097586 | I84: =I$39*($G84/$G$88) -> 0.11319976 | J84: =J$39*($G84/$G$88) -> 0.12904773 | K84: =K$39*($G84/$G$88) -> 0.14453345 | L84: =L$39*($G84/$G$88) -> 0.1589868 | M84: =M$39*($G84/$G$88) -> 0.17170574 | N84: =N$39*($G84/$G$88) -> 0.18200809 | O84: Forecast as FY2026 mix of total non-current liabilities.
A85: Provisions | B85: INR Cr | D85: 0.02 | E85: 0.097 | F85: 0.291 | G85: 1.6117 | H85: =H$39*($G85/$G$88) -> 1.901806 | I85: =I$39*($G85/$G$88) -> 2.206095 | J85: =J$39*($G85/$G$88) -> 2.5149483 | K85: =K$39*($G85/$G$88) -> 2.816742 | L85: =L$39*($G85/$G$88) -> 3.0984162 | M85: =M$39*($G85/$G$88) -> 3.3462895 | N85: =N$39*($G85/$G$88) -> 3.5470669 | O85: Forecast as FY2026 mix of total non-current liabilities.
A86: Deferred tax liabilities, net | B86: INR Cr | D86: 10.731 | E86: 27.969 | F86: 6.19 | G86: 7.3134 | H86: =H$39*($G86/$G$88) -> 8.629812 | I86: =I$39*($G86/$G$88) -> 10.010582 | J86: =J$39*($G86/$G$88) -> 11.412063 | K86: =K$39*($G86/$G$88) -> 12.781511 | L86: =L$39*($G86/$G$88) -> 14.059662 | M86: =M$39*($G86/$G$88) -> 15.184435 | N86: =N$39*($G86/$G$88) -> 16.095501 | O86: Forecast as FY2026 mix of total non-current liabilities.
A87: Other non-current liabilities | B87: INR Cr | D87: 0.101 | E87: 0.094 | F87: 0.087 | G87: 0.0799 | H87: =H$39-SUM(H83:H86) -> 0.094282 | I87: =I$39-SUM(I83:I86) -> 0.10936712 | J87: =J$39-SUM(J83:J86) -> 0.12467852 | K87: =K$39-SUM(K83:K86) -> 0.13963994 | L87: =L$39-SUM(L83:L86) -> 0.15360393 | M87: =M$39-SUM(M83:M86) -> 0.16589225 | N87: =N$39-SUM(N83:N86) -> 0.17584578 | O87: Residual line to tie projected total non-current liabilities exactly.
A88: Total non-current liabilities - bifurcated | B88: INR Cr | D88: =SUM(D83:D87) -> 10.935 | E88: =SUM(E83:E87) -> 28.243 | F88: =SUM(F83:F87) -> 6.651 | G88: =SUM(G83:G87) -> 9.9632 | H88: =SUM(H83:H87) -> 11.756576 | I88: =SUM(I83:I87) -> 13.637628 | J88: =SUM(J83:J87) -> 15.546896 | K88: =SUM(K83:K87) -> 17.412524 | ... N88: =SUM(N83:N87) -> 21.927243 | O88: Sums detailed non-current liability lines and ties to row 39.
A89: Check: NCL bifurcation vs broad total | B89: INR Cr | D89: =D88-D39 -> 0 | E89: =E88-E39 -> 0 | F89: =F88-F39 -> 0 | G89: =G88-G39 -> 0 | H89: =H88-H39 -> 0 | I89: =I88-I39 -> 0 | J89: =J88-J39 -> 0 | K89: =K88-K39 -> 0 | ... N89: =N88-N39 -> 0 | O89: Check against existing broad total row; should be nil.
A91: Current liabilities
A92: Borrowings | B92: INR Cr | D92: 0 | E92: 0 | F92: 0 | G92: 0.8794 | H92: =H$40*($G92/$G$100) -> 1.037692 | I92: =I$40*($G92/$G$100) -> 1.2037227 | J92: =J$40*($G92/$G$100) -> 1.3722439 | K92: =K$40*($G92/$G$100) -> 1.5369132 | L92: =L$40*($G92/$G$100) -> 1.6906045 | M92: =M$40*($G92/$G$100) -> 1.8258528 | N92: =N$40*($G92/$G$100) -> 1.935404 | O92: Forecast as FY2026 mix of total current liabilities.
A93: Lease liabilities | B93: INR Cr | D93: 0 | E93: 0 | F93: 0 | G93: 0 | H93: =H$40*($G93/$G$100) -> 0 | I93: =I$40*($G93/$G$100) -> 0 | J93: =J$40*($G93/$G$100) -> 0 | K93: =K$40*($G93/$G$100) -> 0 | L93: =L$40*($G93/$G$100) -> 0 | M93: =M$40*($G93/$G$100) -> 0 | N93: =N$40*($G93/$G$100) -> 0 | O93: No material FY2026 balance; forecast as FY2026 mix.
A94: Trade payables - MSME | B94: INR Cr | D94: 0 | E94: 0 | F94: 0 | G94: 0 | H94: =H$40*($G94/$G$100) -> 0 | I94: =I$40*($G94/$G$100) -> 0 | J94: =J$40*($G94/$G$100) -> 0 | K94: =K$40*($G94/$G$100) -> 0 | L94: =L$40*($G94/$G$100) -> 0 | M94: =M$40*($G94/$G$100) -> 0 | N94: =N$40*($G94/$G$100) -> 0 | O94: No disclosed FY2026 MSME payable balance; forecast as FY2026 mix.
A95: Trade payables - other creditors | B95: INR Cr | D95: 0.218 | E95: 130.121 | F95: 260.595 | G95: 233.588 | H95: =H$40*($G95/$G$100) -> 275.63384 | I95: =I$40*($G95/$G$100) -> 319.73525 | J95: =J$40*($G95/$G$100) -> 364.49819 | K95: =K$40*($G95/$G$100) -> 408.23797 | L95: =L$40*($G95/$G$100) -> 449.06177 | M95: =M$40*($G95/$G$100) -> 484.98671 | N95: =N$40*($G95/$G$100) -> 514.08591 | O95: Forecast as FY2026 mix of total current liabilities.
A96: Other financial liabilities | B96: INR Cr | D96: 0.362 | E96: 1.429 | F96: 59.075 | G96: 2.821 | H96: =H$40*($G96/$G$100) -> 3.32878 | I96: =I$40*($G96/$G$100) -> 3.8613848 | J96: =J$40*($G96/$G$100) -> 4.4019787 | K96: =K$40*($G96/$G$100) -> 4.9302161 | L96: =L$40*($G96/$G$100) -> 5.4232377 | M96: =M$40*($G96/$G$100) -> 5.8570967 | N96: =N$40*($G96/$G$100) -> 6.2085225 | O96: Forecast as FY2026 mix of total current liabilities.
A97: Other current liabilities | B97: INR Cr | D97: 0.565 | E97: 14.966 | F97: 47.638 | G97: 28.0234 | H97: =H$40*($G97/$G$100) -> 33.067612 | I97: =I$40*($G97/$G$100) -> 38.35843 | J97: =J$40*($G97/$G$100) -> 43.72861 | K97: =K$40*($G97/$G$100) -> 48.976043 | L97: =L$40*($G97/$G$100) -> 53.873648 | M97: =M$40*($G97/$G$100) -> 58.183539 | N97: =N$40*($G97/$G$100) -> 61.674552 | O97: Forecast as FY2026 mix of total current liabilities.
A98: Provisions | B98: INR Cr | D98: 0.013 | E98: 75.257 | F98: 0.03 | G98: 0.0853 | H98: =H$40*($G98/$G$100) -> 0.100654 | I98: =I$40*($G98/$G$100) -> 0.11675864 | J98: =J$40*($G98/$G$100) -> 0.13310485 | K98: =K$40*($G98/$G$100) -> 0.14907743 | L98: =L$40*($G98/$G$100) -> 0.16398517 | M98: =M$40*($G98/$G$100) -> 0.17710399 | N98: =N$40*($G98/$G$100) -> 0.18773023 | O98: Forecast as FY2026 mix of total current liabilities.
A99: Current tax liabilities, net | B99: INR Cr | D99: 0 | E99: 1.867 | F99: 0.385 | G99: 7.7744 | H99: =H$40-SUM(H92:H98) -> 9.173792 | I99: =I$40-SUM(I92:I98) -> 10.641599 | J99: =J$40-SUM(J92:J98) -> 12.131423 | K99: =K$40-SUM(K92:K98) -> 13.587193 | L99: =L$40-SUM(L92:L98) -> 14.945913 | M99: =M$40-SUM(M92:M98) -> 16.141586 | N99: =N$40-SUM(N92:N98) -> 17.110081 | O99: Residual line to tie projected total current liabilities exactly.
A100: Total current liabilities - bifurcated | B100: INR Cr | D100: =SUM(D92:D99) -> 1.158 | E100: =SUM(E92:E99) -> 223.64 | F100: =SUM(F92:F99) -> 367.723 | G100: =SUM(G92:G99) -> 273.1715 | H100: =SUM(H92:H99) -> 322.34237 | I100: =SUM(I92:I99) -> 373.91715 | J100: =SUM(J92:J99) -> 426.26555 | K100: =SUM(K92:K99) -> 477.41742 | ... N100: =SUM(N92:N99) -> 601.2022 | O100: Sums detailed current liability lines and ties to row 40.
A101: Check: CL bifurcation vs broad total | B101: INR Cr | D101: =D100-D40 -> 0 | E101: =E100-E40 -> 0 | F101: =F100-F40 -> 0 | G101: =G100-G40 -> 0 | H101: =H100-H40 -> 0 | I101: =I100-I40 -> 0 | J101: =J100-J40 -> 0 | K101: =K100-K40 -> 0 | ... N101: =N100-N40 -> 0 | O101: Check against existing broad total row; should be nil.
A103: Bifurcation projection note | B103: Note | C103: Historical detailed balance-sheet rows are sourced from the local financial-statement model. Forecast sub-lines use FY2026 mix within each existing broad balance-sheet bucket, with residual lines forcing exact tie-back to the existing total rows so the valuation model remains unchanged.
A106: Cash Flow Statement - Based on PL&BS Bifurcation
A107: Particulars | B107: Unit | C107: FY2022A | D107: FY2023A | E107: FY2024A | F107: FY2025A | G107: FY2026A | H107: FY2027E | I107: FY2028E | J107: FY2029E | K107: FY2030E | L107: FY2031E | M107: FY2032E | N107: FY2033E | O107: Basis
A109: Cash Flow from Operating Activities
A110: NOPAT | B110: INR Cr | E110: =E26 -> 44.307591 | F110: =F26 -> 125.09107 | G110: =G26 -> 190.86072 | H110: =H26 -> 197.84697 | I110: =I26 -> 229.50249 | J110: =J26 -> 261.63283 | K110: =K26 -> 293.02877 | L110: =L26 -> 322.33165 | ... N110: =N26 -> 369.00527 | O110: Linked to P&L NOPAT row.
A111: Add: Depreciation & amortisation | B111: INR Cr | E111: =E22 -> 13.433 | F111: =F22 -> 45.655 | G111: =G22 -> 27.3628 | H111: =H22 -> 30.743634 | I111: =I22 -> 35.662616 | J111: =J22 -> 40.655382 | K111: =K22 -> 45.534028 | L111: =L22 -> 50.087431 | ... N111: =N22 -> 57.340091 | O111: Linked to P&L D&A row.
A112: Less/(Add): Change in operating current assets | B112: INR Cr | E112: =-SUM(E73-D73,E76-D76,E78-D78) -> -146.709 | F112: =-SUM(F73-E73,F76-E76,F78-E78) -> -110.39 | G112: =-SUM(G73-F73,G76-F76,G78-F78) -> -123.8641 | H112: =-SUM(H73-G73,H76-G76,H78-G78) -> -73.689678 | I112: =-SUM(I73-H73,I76-H76,I78-H78) -> -77.292284 | J112: =-SUM(J73-I73,J76-I76,J78-I78) -> -78.451669 | K112: =-SUM(K73-J73,K76-J76,K78-J78) -> -76.658488 | L112: =-SUM(L73-K73,L76-K76,L78-K78) -> -71.547922 | ... N112: =-SUM(N73-M73,N76-M76,N78-M78) -> -50.999359 | O112: Uses trade receivables, other financial assets and other current assets from the bifurcation.
...

Sheet WC Movement
A1: Working Capital Movement
A4: Particulars | B4: FY2026A | C4: FY2027E | D4: FY2028E | E4: FY2029E | F4: FY2030E | G4: FY2031E | H4: FY2032E | I4: FY2033E | J4: Source
A5: Revenue | B5: ='PL&BS'!G6 -> 1042.1571 | C5: ='PL&BS'!H6 -> 1229.7454 | D5: ='PL&BS'!I6 -> 1426.5046 | E5: ='PL&BS'!J6 -> 1626.2153 | F5: ='PL&BS'!K6 -> 1821.3611 | G5: ='PL&BS'!L6 -> 2003.4972 | H5: ='PL&BS'!M6 -> 2163.777 | I5: ='PL&BS'!N6 -> 2293.6036 | J5: Financial workbook / forecast inputs
A6: Target NWC % of Revenue | B6: ='PL&BS'!$G$31 -> 0.0047123288 | C6: 0.01 | D6: =C6 -> 0.01 | E6: =D6 -> 0.01 | F6: =E6 -> 0.01 | G6: =F6 -> 0.01 | H6: =G6 -> 0.01 | I6: =H6 -> 0.01 | J6: FY2026 NWC days and target input
A7: Net Working Capital | B7: =B5*B6 -> 4.9109869 | C7: =C5*C6 -> 12.297454 | D7: =D5*D6 -> 14.265046 | E7: =E5*E6 -> 16.262153 | F7: =F5*F6 -> 18.213611 | G7: =G5*G6 -> 20.034972 | H7: =H5*H6 -> 21.63777 | I7: =I5*I6 -> 22.936036 | J7: Revenue x NWC %
A8: Increase/(Decrease) in NWC | B8: 0 | C8: =C7-B7 -> 7.3864669 | D8: =D7-C7 -> 1.9675926 | E8: =E7-D7 -> 1.9971065 | F8: =F7-E7 -> 1.9514583 | G8: =G7-F7 -> 1.8213611 | H8: =H7-G7 -> 1.6027978 | I8: =I7-H7 -> 1.2982662 | J8: Year-on-year change

Sheet Sources
A1: Sources and Audit Notes
A3: Source ID | B3: Source / URL | C3: Section / Page | D3: Used For | E3: Notes
A4: S1 | B4: outputs/Crizac_Financial_Analysis_5yr/1. crizac_financial_statement_crore_fy2026_analysis.xlsx | C4: Financial Summary; IS; BS; CFS | D4: Historical financials and FY2026 base | E4: Compiled from DRHP.pdf, Q4 FS.pdf and IP Q4.pdf.
A5: S2 | B5: DRHP.pdf | C5: Restated financial information | D5: Historical context | E5: Local source file.
A6: S3 | B6: Quarter Report/Q4 FS.pdf | C6: Audited FY2026 results | D6: FY2026 P&L, balance sheet, cash flow | E6: Local source file.
A7: S4 | B7: Quarter Report/IP Q4.pdf | C7: Investor presentation / KPI pages | D7: Operational context and NWC days | E7: Local source file.
A8: S5 | B8: https://www.ccilindia.com/RiskManagement/SecuritiesSegment/Pages/ZCYC.aspx | C8: Zero Coupon Yield Curve | D8: Risk-free rate reference | E8: Refresh before final use.
A9: S6 | B9: https://pages.stern.nyu.edu/~adamodar/New_Home_Page/data.html | C9: Damodaran data library | D9: ERP / country risk reference | E9: ERP default remains editable.
A10: S7 | B10: Analyst assumptions | C10: Inputs tab | D10: Forecast and terminal assumptions | E10: Review before publication.
A11: Modeling Note | B11: Marketing expenses are not separately disclosed historically; historical marketing is shown as nil with residual operating costs in Other Expenses.
A12: Modeling Note | B12: Broad balance sheet forecast is high-level and ratio/roll-forward based; DCF remains driven by operating FCF assumptions.

Sheet Checks
A1: Model Checks
A4: Check | B4: Actual | C4: Expected | D4: Difference | E4: Tolerance | F4: Status | G4: Notes
A5: Forecast period count | B5: =Inputs!B12 -> 7 | C5: 7 | D5: =B5-C5 -> 0 | E5: 0 | F5: =IF(ABS(D5)<=E5,"OK","Check") -> OK | G5: Must equal 7 years.
A6: Terminal spread positive | B6: =WACC!C23-Inputs!B13 -> 0.1226 | C6: 0 | D6: =B6-C6 -> 0.1226 | E6: 0 | F6: =IF(B6>0,"OK","Check") -> OK | G6: WACC must exceed terminal growth.
A7: PV FCF tie-out | B7: =DCF!E31 -> 1196.6731 | C7: =SUM(DCF!E27:K27) -> 1196.6731 | D7: =B7-C7 -> 0 | E7: 0.01 | F7: =IF(ABS(D7)<=E7,"OK","Check") -> OK | G7: Forecast FCF PV ties to DCF row.
A8: Enterprise value tie-out | B8: =DCF!E33 -> 2404.7248 | C8: =DCF!E31+DCF!E32 -> 2404.7248 | D8: =B8-C8 -> 0 | E8: 0.01 | F8: =IF(ABS(D8)<=E8,"OK","Check") -> OK | G8: EV equals PV FCF plus PV TV.
A9: Equity value bridge | B9: =DCF!E37 -> 2599.0029 | C9: =SUM(DCF!E33:E36) -> 2599.0029 | D9: =B9-C9 -> 0 | E9: 0.01 | F9: =IF(ABS(D9)<=E9,"OK","Check") -> OK | G9: Equity bridge tie-out.
A10: Conclusion tie-out | B10: =Conclusion!E12 -> 2599.0029 | C10: =DCF!E37 -> 2599.0029 | D10: =B10-C10 -> 0 | E10: 0.01 | F10: =IF(ABS(D10)<=E10,"OK","Check") -> OK | G10: Conclusion ties to DCF.
A11: Overall model status | B11: =COUNTIF(F5:F10,"OK") -> 6 | C11: 6 | D11: =B11-C11 -> 0 | E11: 0 | F11: =IF(B11=C11,"OK","Check") -> OK | G11: All key checks should pass.
