Workbook
Name IQ_CH: 110000
Name IQ_CQ: 5000
Name IQ_CY: 10000
Name IQ_DAILY: 500000
Name IQ_FH: 100000
Name IQ_FQ: 500
Name IQ_FY: 1000
Name IQ_LTM: 2000
Name IQ_MONTH: 15000
Name IQ_NTM: 6000
Name IQ_WEEK: 50000
Name IQ_YTD: 3000

Sheet Cover
A1: Crizac Limited - CCM Valuation Workbook
A2: Comparable Company Method using EV/Revenue and EV/EBITDA
A4: Workbook purpose | B4: Formula-driven valuation add-on for the Crizac research pack. All figures are in Rs crore unless stated otherwise.
A6: Key Outputs
B7: =Inputs!B8 -> 199
B8: =Inputs!B18 -> 3.2118005
B9: =Inputs!B19 -> 11.852727
B10: =Valuation!H9 -> 247.98161
B11: =Valuation!H14 -> 277.66156
B12: =ROUND(Inputs!B24,0)&" - "&ROUND(Inputs!B25,0)&" per share" -> 245 - 280 per share
B13: =Checks!F11 -> OK
A16: Color legend
A17: Blue font | B17: Editable assumptions / inputs
A18: Black font | B18: Formulas and calculations
A19: Green font | B19: Linked references to other sheets

Sheet Inputs
A1: Inputs and Core Assumptions
A2: Editable source inputs for the CCM valuation
A4: Crizac market data
A5: Financial unit | B5: Rs crore | C5: Text
A6: Valuation date | B6: 46209 | C6: Text
A7: Market data source date | B7: 03 July close for Crizac; 06 July for comps where available | C7: Text
A8: Current price used (Rs/share) | B8: 199 | C8: Per share
A9: Market capitalisation | B9: 3481 | C9: Currency
A10: Shares outstanding | B10: 17.5 | C10: Count
A11: FY26 revenue | B11: 1042.16 | C11: Currency
A12: FY26 EBITDA | B12: 282.4 | C12: Currency
A13: Cash and cash equivalents | B13: 135.54 | C13: Currency
A14: Borrowings | B14: 1.75 | C14: Currency
A16: Derived Crizac trading multiples
A17: Enterprise value | B17: =B9+B14-B13 -> 3347.21
A18: Current EV/Revenue | B18: =B17/B11 -> 3.2118005
A19: Current EV/EBITDA | B19: =B17/B12 -> 11.852727
A21: Valuation settings
A22: EV/Revenue weighting | B22: 0.4
A23: EV/EBITDA weighting | B23: =1-B22 -> 0.6
A24: Selected low value/share | B24: 245
A25: Selected high value/share | B25: 280

Sheet Valuation
B2: CCM Valuation Bridge
B3: Peer mean and median multiple outputs
B5: Method | C5: Applied Multiple | D5: Crizac Metric | E5: Implied EV | F5: Net Cash | G5: Equity Value | H5: Value/Share | I5: Weighting
B6: EV/Revenue - peer mean | C6: =Comps!K13 -> 4.3941394 | D6: =Inputs!B11 -> 1042.16 | E6: =C6*D6 -> 4579.3963 | F6: =Inputs!B13-Inputs!B14 -> 133.79 | G6: =E6+F6 -> 4713.1863 | H6: =G6/Inputs!B10 -> 269.32493 | I6: =Inputs!B22 -> 0.4
B7: EV/EBITDA - peer mean | C7: =Comps!L13 -> 14.011625 | D7: =Inputs!B12 -> 282.4 | E7: =C7*D7 -> 3956.8829 | F7: =Inputs!B13-Inputs!B14 -> 133.79 | G7: =E7+F7 -> 4090.6729 | H7: =G7/Inputs!B10 -> 233.75274 | I7: =Inputs!B23 -> 0.6
B9: Mean multiple result | H9: =SUMPRODUCT(H6:H7,I6:I7) -> 247.98161
B11: EV/Revenue - peer median | C11: =Comps!K14 -> 4.8387508 | D11: =Inputs!B11 -> 1042.16 | E11: =C11*D11 -> 5042.7525 | F11: =Inputs!B13-Inputs!B14 -> 133.79 | G11: =E11+F11 -> 5176.5425 | H11: =G11/Inputs!B10 -> 295.80243 | I11: =Inputs!B22 -> 0.4
B12: EV/EBITDA - peer median | C12: =Comps!L14 -> 15.983158 | D12: =Inputs!B12 -> 282.4 | E12: =C12*D12 -> 4513.6438 | F12: =Inputs!B13-Inputs!B14 -> 133.79 | G12: =E12+F12 -> 4647.4338 | H12: =G12/Inputs!B10 -> 265.56765 | I12: =Inputs!B23 -> 0.6
B14: Median multiple result | H14: =SUMPRODUCT(H11:H12,I11:I12) -> 277.66156
B17: Selected CCM valuation range
B18: Low | C18: =Inputs!B24 -> 245
B19: High | C19: =Inputs!B25 -> 280
B20: Current price discount / premium to midpoint | C20: =Inputs!B8/AVERAGE(C18:C19)-1 -> -0.24190476

Sheet Comps
B2: Comparable Company Multiples
B3: EV/Revenue and EV/EBITDA proxy peer set
B5: Company | C5: Currency | D5: Market Data Date | E5: Market Cap | F5: Debt/Borrowings | G5: Cash/Investments | H5: Enterprise Value | I5: Revenue | J5: EBITDA | K5: EV/Revenue | L5: EV/EBITDA | M5: Included?
B6: IDP Education | C6: A | D6: 46209 | E6: 629 | F6: 286.582 | G6: 121.481 | H6: =E6+F6-G6 -> 794.101 | I6: 882.201 | J6: =I6-729.143 -> 153.058 | K6: =H6/I6 -> 0.90013614 | L6: =H6/J6 -> 5.1882358 | M6: Yes
B7: IndiaMART | C7: Rs cr | D7: 46209 | E7: 11361 | F7: 23 | G7: 3792 | H7: =E7+F7-G7 -> 7592 | I7: 1569 | J7: 475 | K7: =H7/I7 -> 4.8387508 | L7: =H7/J7 -> 15.983158 | M7: Yes
B8: Info Edge | C8: Rs cr | D8: 46209 | E8: 66492 | F8: 259 | G8: 42299 | H8: =E8+F8-G8 -> 24452 | I8: 3285 | J8: 1172 | K8: =H8/I8 -> 7.4435312 | L8: =H8/J8 -> 20.863481 | M8: Yes
B9: Just Dial | C9: Rs cr | D9: Reviewed | E9: 0 | F9: 85 | G9: 4608 | H9: =E9+F9-G9 -> -4523 | I9: 1043 | J9: 217 | K9: =H9/I9 -> -4.3365292 | L9: =H9/J9 -> -20.843318 | M9: No - outlier
B12: Summary multiples
B13: Included peer mean | K13: =AVERAGE(K6:K8) -> 4.3941394 | L13: =AVERAGE(L6:L8) -> 14.011625
B14: Included peer median | K14: =MEDIAN(K6:K8) -> 4.8387508 | L14: =MEDIAN(L6:L8) -> 15.983158
B17: Notes
B18: IDP is the closest global student-placement peer but includes testing and teaching exposure. IndiaMART and Info Edge are Indian platform proxies. Just Dial was reviewed but excluded because its EV is distorted by cash/investments and visible annuals are stale.

Sheet Sensitivity
A1: Sensitivity Tables
A2: EV/Revenue and EV/EBITDA valuation sensitivities
A4: EV/Revenue Sensitivity | D4: EV/EBITDA Sensitivity
A5: EV/Revenue | B5: Value/Share | D5: EV/EBITDA | E5: Value/Share
A6: 3.21 | B6: =((Inputs!B11*A6)+Inputs!B13-Inputs!B14)/Inputs!B10 -> 198.80706 | D6: 11.85 | E6: =((Inputs!B12*D6)+Inputs!B13-Inputs!B14)/Inputs!B10 -> 198.87029
A7: 4 | B7: =((Inputs!B11*A7)+Inputs!B13-Inputs!B14)/Inputs!B10 -> 245.85314 | D7: 14.01 | E7: =((Inputs!B12*D7)+Inputs!B13-Inputs!B14)/Inputs!B10 -> 233.72651
A8: 4.39 | B8: =((Inputs!B11*A8)+Inputs!B13-Inputs!B14)/Inputs!B10 -> 269.07842 | D8: 14.71 | E8: =((Inputs!B12*D8)+Inputs!B13-Inputs!B14)/Inputs!B10 -> 245.02251
A9: 4.84 | B9: =((Inputs!B11*A9)+Inputs!B13-Inputs!B14)/Inputs!B10 -> 295.87682 | D9: 15.98 | E9: =((Inputs!B12*D9)+Inputs!B13-Inputs!B14)/Inputs!B10 -> 265.51669
A10: 6.14 | B10: =((Inputs!B11*A10)+Inputs!B13-Inputs!B14)/Inputs!B10 -> 373.29442 | D10: 18.42 | E10: =((Inputs!B12*D10)+Inputs!B13-Inputs!B14)/Inputs!B10 -> 304.89131
A13: Interpretation
A14: The selected CCM range uses blended peer mean and median outputs with 60% weight to EV/EBITDA and 40% weight to EV/Revenue. EV/EBITDA receives higher weight because Crizac is already profitable and margin quality is central to valuation.

Sheet Checks
A1: Model Checks
A2: Formula and valuation sanity checks
A4: Check | B4: Actual | C4: Expected | D4: Difference | E4: Tolerance | F4: Status
A5: Weighting sums to 100% | B5: =Inputs!B22+Inputs!B23 -> 1 | C5: 1 | D5: =B5-C5 -> 0 | E5: 0.0001 | F5: =IF(ABS(D5)<=E5,"OK","Check") -> OK
A6: Enterprise value bridge ties | B6: =Inputs!B17 -> 3347.21 | C6: =Inputs!B9+Inputs!B14-Inputs!B13 -> 3347.21 | D6: =B6-C6 -> 0 | E6: 0.1 | F6: =IF(ABS(D6)<=E6,"OK","Check") -> OK
A7: Median valuation above mean | B7: =Valuation!H14 -> 277.66156 | C7: =Valuation!H9 -> 247.98161 | D7: =B7-C7 -> 29.679945 | E7: 0 | F7: =IF(B7>=C7,"OK","Check") -> OK
A8: Revenue and EBITDA positive | B8: =Inputs!B11+Inputs!B12 -> 1324.56 | C8: 0 | D8: =B8-C8 -> 1324.56 | E8: 0 | F8: =IF(B8>C8,"OK","Check") -> OK
A11: Overall model status | F11: =IF(COUNTIF(F5:F8,"Check")=0,"OK","Review checks") -> OK

Sheet Sources
A1: Sources and Audit Trail
A2: Source URLs and notes for CCM valuation inputs
A4: Item | B4: Value / figure | C4: Units | D4: Period / date | E4: Source | F4: URL / file | G4: Notes
A5: Crizac current price
A6: Crizac market cap
A7: Crizac FY26 revenue
A8: Crizac FY26 EBITDA
A9: Crizac cash / borrowings
A10: IDP share price
A11: IDP FY25 financials
A12: IndiaMART peer data
A13: Info Edge peer data
A14: Just Dial outlier
